bigtiff/__init__.py
bigtiff/image2d.py
bigtiff/lzw_decompress_py.py
bigtiff/memmap.py
bigtiff/representation.py
bigtiff/strip.py
bigtiff/tif_format.py
bigtiff/tiff.py
bigtiff/writer.py
bigtiff-0.1.0.dist-info/LICENSE
bigtiff-0.1.0.dist-info/METADATA
bigtiff-0.1.0.dist-info/WHEEL
bigtiff-0.1.0.dist-info/top_level.txt
bigtiff-0.1.0.dist-info/RECORD
