Metadata-Version: 2.1
Name: bigtiff
Version: 0.1.0
Summary: A library for random access for large (Big-)TIFF files
Home-page: UNKNOWN
Author: Manuel Schölling
Author-email: manuel.schoelling@dzne.de
License: GPL3
Platform: UNKNOWN
Requires-Dist: numpy
Requires-Dist: kaitaistruct (==0.8.0)
